[{"size": 3, "solutions": [[["BR", "CN", "IN", "NG", "PH", "PK", "TR", "US", "VN"], ["MX", "PH", "RU"], ["DE"]], [["BJ", "FM", "GM", "MT", "PW", "SM", "TT"], ["BH", "BY", "MC", "MH", "MV", "UY"], ["GD", "GH", "GM", "GW"]], [["BO", "BR", "EC"], ["UY"], ["GY"]]], "alternativeSolutions": [[[], [], []], [[], [], []], [["TT"], [], []]], "rows": [{"category": "top_20_population", "value": true}, {"category": "elevation_sub1k", "value": true}, {"category": "continent", "value": "SA"}], "cols": [{"category": "capital_not_largest", "value": true}, {"category": "capital_starting_letter", "value": "M"}, {"category": "starting_letter", "value": "G"}], "data": {"maxCellDifficulty": 5.843784962932873, "avgCellDifficulty": 4.203320181218494, "difficultyLevel": "medium"}}, {"size": 3, "solutions": [[["AG", "AO", "BB", "BE", "BN", "BS", "DE", "DM", "EG", "GH", "GW", "GY", "JM", "KN", "LC", "MZ", "PG", "SS", "ST", "SZ", "TL", "TZ", "UG", "VU", "ZA", "ZW"], ["BR", "CD", "CN", "DE", "EG", "ET", "PH", "VN"], ["CM", "NR"]], [["AG", "BB", "BN", "BS", "DM", "JM", "KN", "LC", "PG", "ST", "TL", "TT", "VU"], ["ID", "JP", "PH"], ["NR"]], [["AF", "BW", "LS", "MW", "SS", "SZ", "UG", "ZM", "ZW"], ["ET"], ["AM"]]], "alternativeSolutions": [[["EC"], [], []], [[], [], []], [[], [], []]], "rows": [{"category": "flag_colors", "value": "Yellow/Gold"}, {"category": "island", "value": true}, {"category": "landlocked", "value": true}], "cols": [{"category": "flag_colors", "value": "Black"}, {"category": "top_20_population", "value": true}, {"category": "capital_starting_letter", "value": "Y"}], "data": {"maxCellDifficulty": 7.515830804314692, "avgCellDifficulty": 4.406411917518348, "difficultyLevel": "hard"}}, {"size": 3, "solutions": [[["AD", "AG", "BB", "LC", "LI", "MH", "NR", "PW", "SC", "SM", "TV", "VC"], ["BA", "BB", "BR", "BS", "BW", "BZ"], ["AR", "AU", "BR", "CD", "IN", "KZ", "MN", "RU", "TD", "US"]], [["AD", "LI", "SM", "VA"], ["BF", "BI", "BO", "BT", "BW", "BY"], ["KZ", "MN", "TD"]], [["AD", "LI", "MC", "MT", "SM", "VA"], ["BA", "BE", "BG", "BY"], ["RU"]]], "alternativeSolutions": [[[], [], []], [[], [], []], [[], [], []]], "rows": [{"category": "flag_colors", "value": "Blue"}, {"category": "landlocked", "value": true}, {"category": "continent", "value": "EU"}], "cols": [{"category": "bottom_20_area", "value": true}, {"category": "starting_letter", "value": "B"}, {"category": "top_20_area", "value": true}], "data": {"maxCellDifficulty": 6.458534367123542, "avgCellDifficulty": 4.115132942760129, "difficultyLevel": "medium"}}, {"size": 3, "solutions": [[["TO", "TV"], ["AG", "DM", "GD", "KN", "LC", "VC"], ["AG", "DM", "KN", "LC"]], [["TH", "TR"], ["MX", "US"], ["DE", "EG"]], [["TN", "TW"], ["HN"], ["AL", "EE", "LY"]]], "alternativeSolutions": [[[], [], []], [[], [], []], [[], [], []]], "rows": [{"category": "bottom_20_population", "value": true}, {"category": "top_20_population", "value": true}, {"category": "capital_starting_letter", "value": "T"}], "cols": [{"category": "starting_letter", "value": "T"}, {"category": "continent", "value": "NA"}, {"category": "flag_colors", "value": "Black"}], "data": {"maxCellDifficulty": 7.627824536154664, "avgCellDifficulty": 4.7299383871643155, "difficultyLevel": "hard"}}, {"size": 3, "solutions": [[["FM", "LI", "PW", "SM"], ["KN"], ["AG", "DM", "KN", "LC"]], [["BO", "CA", "CN", "EC", "IN", "KZ", "MM", "PK", "TR", "TZ", "US"], ["AR", "CN", "CO", "KG"], ["AF", "KE", "TZ", "UG"]], [["CI", "IL", "IN"], ["IQ"], ["IQ"]]], "alternativeSolutions": [[[], [], []], [[], [], ["EC"]], [[], [], []]], "rows": [{"category": "bottom_20_population", "value": true}, {"category": "elevation_sup5k", "value": true}, {"category": "starting_letter", "value": "I"}], "cols": [{"category": "capital_not_largest", "value": true}, {"category": "capital_starting_letter", "value": "B"}, {"category": "flag_colors", "value": "Black"}], "data": {"maxCellDifficulty": 7.354362720789512, "avgCellDifficulty": 4.5922413040315995, "difficultyLevel": "hard"}}, {"size": 3, "solutions": [[["AD", "LI", "MC", "SM", "VA"], ["XK"], ["IE"]], [["SC"], ["KE"], ["DJ", "SN", "TZ"]], [["AG", "DM", "FM", "KI", "KN", "LC", "MC", "MH", "NR", "SC", "SM", "TO", "TV", "VA", "WS"], ["KE", "KI", "KW", "XK"], ["DJ", "IE", "QA", "SY", "TJ", "TL"]]], "alternativeSolutions": [[[], [], []], [[], [], []], [[], [], []]], "rows": [{"category": "continent", "value": "EU"}, {"category": "continent", "value": "AF"}, {"category": "flag_colors", "value": "White"}], "cols": [{"category": "bottom_20_population", "value": true}, {"category": "starting_letter", "value": "K"}, {"category": "capital_starting_letter", "value": "D"}], "data": {"maxCellDifficulty": 6.640220599322197, "avgCellDifficulty": 4.6403444432791225, "difficultyLevel": "hard"}}, {"size": 3, "solutions": [[["AU", "FJ", "KI", "NZ", "PG", "TO", "TV", "VU", "WS"], ["AU"], ["FM", "KI", "MH", "NR", "PW", "TV"]], [["AG", "BZ", "CA", "CR", "CU", "DM", "DO", "GD", "HT", "KN", "MX", "PA", "TT", "US"], ["CA", "MX", "US"], ["AG", "BB", "BS", "GD", "LC", "TT"]], [["KE", "MM", "MR", "TD", "TO"], ["IN", "TD"], ["BS", "MR", "PW"]]], "alternativeSolutions": [[["TL"], [], []], [[], [], []], [[], ["KZ"], []]], "rows": [{"category": "continent", "value": "OC"}, {"category": "continent", "value": "NA"}, {"category": "capital_starting_letter", "value": "N"}], "cols": [{"category": "flag_colors", "value": "Red"}, {"category": "top_20_area", "value": true}, {"category": "elevation_sub1k", "value": true}], "data": {"maxCellDifficulty": 7.681381816184457, "avgCellDifficulty": 4.342697906969753, "difficultyLevel": "hard"}}, {"size": 3, "solutions": [[["BR", "CD", "CN", "ID", "IN", "IR", "MX", "RU", "US"], ["RU"], ["SA"]], [["BR", "CD", "CN", "DE", "EG", "ET", "PH", "VN"], ["AD", "BA", "BE", "CY", "DE", "ES", "LI", "LT", "MD", "ME", "MK", "RO", "SE", "UA", "VA", "XK"], ["DM"]], [["TH"], ["CH", "FI", "IE", "IS", "PL"], ["IS"]]], "alternativeSolutions": [[[], [], []], [[], ["FI", "PT", "RS", "SI", "SM"], []], [[], [], []]], "rows": [{"category": "top_20_area", "value": true}, {"category": "flag_colors", "value": "Yellow/Gold"}, {"category": "ending_letter", "value": "D"}], "cols": [{"category": "top_20_population", "value": true}, {"category": "continent", "value": "EU"}, {"category": "capital_starting_letter", "value": "R"}], "data": {"maxCellDifficulty": 6.291441075956407, "avgCellDifficulty": 3.3371602079501916, "difficultyLevel": "medium"}}, {"size": 3, "solutions": [[["CD", "KE", "TZ", "UG"], ["SC"], ["BF", "BI", "BW", "CF", "ET", "LS", "ML", "MW", "NE", "RW", "SS", "SZ", "TD", "UG", "ZM", "ZW"]], [["TJ", "TR", "TZ"], ["TO", "TV"], ["TJ", "TM"]], [["IR", "US"], ["NR", "VC"], ["AM", "CH", "PY"]]], "alternativeSolutions": [[[], [], []], [[], [], []], [["KZ"], [], ["KZ"]]], "rows": [{"category": "continent", "value": "AF"}, {"category": "starting_letter", "value": "T"}, {"category": "capital_ending_letter", "value": "N"}], "cols": [{"category": "elevation_sup5k", "value": true}, {"category": "bottom_20_population", "value": true}, {"category": "landlocked", "value": true}], "data": {"maxCellDifficulty": 8.666386506781716, "avgCellDifficulty": 5.515692277014718, "difficultyLevel": "hard"}}, {"size": 3, "solutions": [[["AO", "DZ"], ["BI", "BJ", "CI", "CM", "GM", "GQ", "MA", "NG", "TZ", "ZA"], ["KE", "MR", "NE", "TD"]], [["AR", "AU", "DZ"], ["AU", "BR", "CA", "CN", "IN", "KZ", "US"], ["IN", "TD"]], [["AD", "AF", "AM", "AT", "AZ"], ["BI", "BO", "CH", "KZ", "LI", "SM"], ["NE", "TD"]]], "alternativeSolutions": [[[], [], []], [[], [], ["KZ"]], [[], [], ["KZ"]]], "rows": [{"category": "continent", "value": "AF"}, {"category": "top_20_area", "value": true}, {"category": "landlocked", "value": true}], "cols": [{"category": "starting_letter", "value": "A"}, {"category": "capital_not_largest", "value": true}, {"category": "capital_starting_letter", "value": "N"}], "data": {"maxCellDifficulty": 5.853610884997531, "avgCellDifficulty": 3.9178325027661742, "difficultyLevel": "medium"}}, {"size": 3, "solutions": [[["DM"], ["DM", "IS"], ["MA"]], [["CF", "CM", "CN", "CO", "CV", "CY", "KM", "TD"], ["CU", "CV", "CY", "KM"], ["CA", "CM", "CN"]], [["FJ", "KI", "NR", "PG", "PW", "SB", "TV", "VU"], ["FJ", "FM", "KI", "MH", "NR", "NZ", "PG", "PW", "SB", "TO", "TV", "VU", "WS"], ["AU", "FM", "NZ", "PW"]]], "alternativeSolutions": [[[], [], []], [[], [], ["CI"]], [["TL"], ["AU", "TL"], []]], "rows": [{"category": "capital_starting_letter", "value": "R"}, {"category": "starting_letter", "value": "C"}, {"category": "continent", "value": "OC"}], "cols": [{"category": "flag_colors", "value": "Yellow/Gold"}, {"category": "island", "value": true}, {"category": "capital_not_largest", "value": true}], "data": {"maxCellDifficulty": 6.291441075956407, "avgCellDifficulty": 4.685048706698755, "difficultyLevel": "hard"}}, {"size": 3, "solutions": [[["PK"], ["PH"], ["PE"]], [["BH", "JP", "TW"], ["BH", "KM", "MH", "MV", "PH"], ["ID"]], [["BJ", "CM", "KZ", "LI", "PK", "TW"], ["GQ", "PH"], ["AU", "BR", "CA", "CN", "IN", "KZ", "US"]]], "alternativeSolutions": [[[], [], ["CN"]], [[], [], ["AU"]], [[], [], []]], "rows": [{"category": "starting_letter", "value": "P"}, {"category": "island", "value": true}, {"category": "capital_not_largest", "value": true}], "cols": [{"category": "ending_letter", "value": "N"}, {"category": "capital_starting_letter", "value": "M"}, {"category": "top_20_area", "value": true}], "data": {"maxCellDifficulty": 4.905329472815452, "avgCellDifficulty": 3.801262945201054, "difficultyLevel": "medium"}}, {"size": 3, "solutions": [[["AD", "AG", "AM", "AR", "AU", "AZ"], ["KI", "KZ", "XK"], ["AD", "BA", "CZ", "EE", "FI", "FR", "GB", "GR", "HR", "IS", "LI", "LU", "MD", "NL", "NO", "RO", "RS", "RU", "SE", "SI", "SK", "SM", "UA", "XK"]], [["AG"], ["KI", "KW"], ["BE", "BY", "DK", "EE", "LT", "LU", "LV", "MC", "MD", "MT", "NL", "SM", "VA"]], [["AG"], ["KI"], ["CY", "GB", "IE", "IS", "MT"]]], "alternativeSolutions": [[[], [], ["AM", "AZ", "ME", "PT"]], [[], [], []], [["AU"], [], []]], "rows": [{"category": "flag_colors", "value": "Blue"}, {"category": "elevation_sub1k", "value": true}, {"category": "island", "value": true}], "cols": [{"category": "starting_letter", "value": "A"}, {"category": "starting_letter", "value": "K"}, {"category": "continent", "value": "EU"}], "data": {"maxCellDifficulty": 6.965191658178371, "avgCellDifficulty": 4.592850547330387, "difficultyLevel": "hard"}}, {"size": 3, "solutions": [[["AE", "BI", "BJ", "BO", "BR", "CI", "CM", "GM", "GQ", "IN", "LK", "MA", "MM", "NG", "PK", "TZ", "ZA"], ["CH", "LI", "MT", "SM"], ["BJ", "CM", "KZ", "LI", "PK", "TW"]], [["BR", "DZ", "IN", "IR", "LY", "MX", "SA", "SD"], ["RU"], ["IR", "KZ", "SD"]], [["CY", "DM", "GD", "IE", "JM", "KM", "KN", "LK", "MG", "MU", "MV", "SB", "SC", "ST", "VC", "VU"], ["CY", "GB", "IE", "IS", "MT"], ["BH", "JP", "TW"]]], "alternativeSolutions": [[["BZ", "SM"], ["TR"], []], [[], [], []], [["HT"], [], []]], "rows": [{"category": "capital_not_largest", "value": true}, {"category": "top_20_area", "value": true}, {"category": "island", "value": true}], "cols": [{"category": "flag_colors", "value": "Green"}, {"category": "continent", "value": "EU"}, {"category": "ending_letter", "value": "N"}], "data": {"maxCellDifficulty": 4.042792560693977, "avgCellDifficulty": 3.2334235923930787, "difficultyLevel": "easy"}}, {"size": 3, "solutions": [[["CF", "CL", "CO", "CR", "CU", "CV", "CZ", "HR", "KH", "KM", "TD"], ["CA", "CM", "CN"], ["CN"]], [["AD", "AM", "AZ", "BW", "CF", "CZ", "ET", "KZ", "LA", "LI", "LS", "LU", "MD", "MN", "NP", "PY", "RS", "RW", "SK", "SM", "SS", "SZ", "TD", "UZ", "XK"], ["BI", "BO", "CH", "KZ", "LI", "SM"], ["ET"]], [["AG", "BB", "BS", "BZ", "CR", "CU", "DO", "GT", "HN", "HT", "LC", "NI", "PA", "SV", "US", "VC"], ["BZ", "CA", "TT", "US"], ["MX", "US"]]], "alternativeSolutions": [[[], ["CI"], []], [[], [], []], [[], [], []]], "rows": [{"category": "starting_letter", "value": "C"}, {"category": "landlocked", "value": true}, {"category": "continent", "value": "NA"}], "cols": [{"category": "flag_colors", "value": "Blue"}, {"category": "capital_not_largest", "value": true}, {"category": "top_20_population", "value": true}], "data": {"maxCellDifficulty": 4.224137722912447, "avgCellDifficulty": 2.923694220555647, "difficultyLevel": "easy"}}, {"size": 3, "solutions": [[["BR", "DZ", "IN", "IR", "LY", "MX", "SA", "SD"], ["KZ", "MN", "TD"], ["AU", "BR", "CA", "CN", "IN", "KZ", "US"]], [["BF", "BJ", "BY", "GD", "GH", "GM", "GW", "KW", "LT", "MR", "MU", "MV", "SC", "SN", "TG"], ["BF", "BY", "LU", "MD", "PY", "SM", "VA"], ["BJ", "FM", "GM", "MT", "PW", "SM", "TT"]], [["LT", "SC"], ["AT", "LA", "LI", "VA"], ["LI", "MT"]]], "alternativeSolutions": [[[], [], []], [["PY", "SM"], [], []], [[], [], []]], "rows": [{"category": "top_20_area", "value": true}, {"category": "elevation_sub1k", "value": true}, {"category": "capital_starting_letter", "value": "V"}], "cols": [{"category": "flag_colors", "value": "Green"}, {"category": "landlocked", "value": true}, {"category": "capital_not_largest", "value": true}], "data": {"maxCellDifficulty": 5.831441293001876, "avgCellDifficulty": 4.4554509828048685, "difficultyLevel": "hard"}}, {"size": 3, "solutions": [[["ID"], ["DO"], ["AG", "BB", "BH", "GD", "KN", "LC", "MH", "MT", "MV", "NR", "PW", "SC", "SG", "TV", "VC"]], [["CD", "DZ", "LY", "SD", "TD"], ["CF"], ["SC"]], [["RU"], ["CZ"], ["AD", "LI", "MC", "MT", "SM", "VA"]]], "alternativeSolutions": [[["AU"], [], []], [[], [], []], [[], [], []]], "rows": [{"category": "island", "value": true}, {"category": "continent", "value": "AF"}, {"category": "continent", "value": "EU"}], "cols": [{"category": "top_20_area", "value": true}, {"category": "ending_letter", "value": "C"}, {"category": "bottom_20_area", "value": true}], "data": {"maxCellDifficulty": 6.531535721998516, "avgCellDifficulty": 4.739408077414274, "difficultyLevel": "hard"}}, {"size": 3, "solutions": [[["AD"], ["DZ", "KZ"], ["AE", "DZ", "GR", "JO", "MG", "NG", "NL", "PY", "TM", "TR", "WS"]], [["AD", "LI", "MC", "MT", "SM", "VA"], ["RU"], ["AT", "BA", "BG", "BY", "CH", "CY", "CZ", "DK", "EE", "FI", "FR", "GB", "GR", "HR", "HU", "IE", "IS", "IT", "LU", "LV", "MC", "MT", "NL", "NO", "PL", "RS", "RU", "SI", "SK", "SM", "VA", "XK"]], [["MH", "NR", "PW", "TV"], ["AU"], ["AU", "FJ", "FM", "KI", "MH", "NR", "NZ", "PG", "SB", "TO", "TV", "WS"]]], "alternativeSolutions": [[[], [], ["CI"]], [[], [], ["AZ", "GE", "PT", "TR"]], [[], [], ["TL"]]], "rows": [{"category": "capital_starting_letter", "value": "A"}, {"category": "continent", "value": "EU"}, {"category": "continent", "value": "OC"}], "cols": [{"category": "bottom_20_area", "value": true}, {"category": "top_20_area", "value": true}, {"category": "flag_colors", "value": "White"}], "data": {"maxCellDifficulty": 8.08798374048573, "avgCellDifficulty": 4.194689276837133, "difficultyLevel": "medium"}}, {"size": 3, "solutions": [[["US"], ["US"], ["UG", "US"]], [["CD", "EG", "ET", "NG"], ["CD", "DZ", "LY", "SD", "TD"], ["CD", "KE", "TZ", "UG"]], [["BD", "CN", "ID", "IN", "IR", "JP", "PH", "PK", "TH", "TR", "VN"], ["CN", "ID", "IN", "IR", "KZ", "MN", "SA"], ["AF", "BT", "CN", "GE", "IN", "IR", "KG", "KZ", "MM", "NP", "PK", "TJ", "TR"]]], "alternativeSolutions": [[[], [], []], [[], [], []], [["EG", "RU"], ["RU"], ["RU"]]], "rows": [{"category": "starting_letter", "value": "U"}, {"category": "continent", "value": "AF"}, {"category": "continent", "value": "AS"}], "cols": [{"category": "top_20_population", "value": true}, {"category": "top_20_area", "value": true}, {"category": "elevation_sup5k", "value": true}], "data": {"maxCellDifficulty": 4.110617289775381, "avgCellDifficulty": 2.4618972888188195, "difficultyLevel": "easy"}}, {"size": 3, "solutions": [[["AR", "BR", "PE"], ["BO", "PY"], ["PY", "UY"]], [["BR", "CD", "CN", "ID", "IN", "IR", "MX", "RU", "US"], ["ET"], ["DE"]], [["BR", "DZ", "IN", "IR", "LY", "MX", "SA", "SD"], ["AF", "AZ", "BF", "BI", "BO", "BY", "CF", "ET", "HU", "LS", "ML", "MW", "NE", "RW", "SS", "TJ", "TM", "UZ", "ZM", "ZW"], ["HU", "IT"]]], "alternativeSolutions": [[[], [], []], [[], [], ["TR"]], [[], ["PY", "SM"], ["PS", "PY"]]], "rows": [{"category": "continent", "value": "SA"}, {"category": "top_20_population", "value": true}, {"category": "flag_colors", "value": "Green"}], "cols": [{"category": "top_20_area", "value": true}, {"category": "landlocked", "value": true}, {"category": "ending_letter", "value": "Y"}], "data": {"maxCellDifficulty": 4.611480897990123, "avgCellDifficulty": 3.2522963345796523, "difficultyLevel": "easy"}}, {"size": 3, "solutions": [[["PE", "PK"], ["AR", "CA", "CD", "CN", "IN", "IR", "KZ", "MX", "PE", "RU", "US"], ["TJ", "TR", "TZ"]], [["PH", "PK", "PS"], ["CN", "ID", "IN", "IR", "KZ", "MN", "SA"], ["TH", "TJ", "TL", "TM", "TR", "TW"]], [["PG", "PH", "PW"], ["ID"], ["TL", "TO", "TT", "TV", "TW"]]], "alternativeSolutions": [[["CN"], [], []], [["CN"], ["RU"], []], [[], ["AU"], []]], "rows": [{"category": "elevation_sup5k", "value": true}, {"category": "continent", "value": "AS"}, {"category": "island", "value": true}], "cols": [{"category": "starting_letter", "value": "P"}, {"category": "top_20_area", "value": true}, {"category": "starting_letter", "value": "T"}], "data": {"maxCellDifficulty": 4.446027257083677, "avgCellDifficulty": 3.3153809551928393, "difficultyLevel": "easy"}}, {"size": 3, "solutions": [[["LY", "SD"], ["AG", "BB", "BE", "BS", "EE", "GH", "GW", "KW", "LC", "TT"], ["AF", "KE", "TZ", "UG"]], [["CN", "ID", "IN", "IR", "KZ", "MN", "SA"], ["BH", "KW", "MV", "QA", "SG"], ["AF", "BT", "CN", "GE", "IN", "IR", "KG", "KZ", "MM", "NP", "PK", "TJ", "TR"]], [["CA", "MX", "US"], ["AG", "BB", "BS", "GD", "LC", "TT"], ["CA", "MX", "US"]]], "alternativeSolutions": [[[], [], ["EC"]], [["RU"], [], ["RU"]], [[], [], []]], "rows": [{"category": "flag_colors", "value": "Black"}, {"category": "continent", "value": "AS"}, {"category": "continent", "value": "NA"}], "cols": [{"category": "top_20_area", "value": true}, {"category": "elevation_sub1k", "value": true}, {"category": "elevation_sup5k", "value": true}], "data": {"maxCellDifficulty": 5.7391511887965185, "avgCellDifficulty": 3.510497435655107, "difficultyLevel": "easy"}}, {"size": 3, "solutions": [[["BF", "BY", "LU", "MD", "PY", "SM", "VA"], ["FM", "KI", "MH", "NR", "PW", "TV"], ["SN"]], [["KZ", "MN", "TD"], ["AU"], ["BR"]], [["AD", "BF", "BO", "BT", "CF", "ET", "KG", "KZ", "LI", "MD", "MK", "ML", "MN", "RW", "SS", "SZ", "TD", "TJ", "UG", "VA", "XK", "ZW"], ["FJ", "KI", "NR", "PG", "PW", "SB", "TV", "VU"], ["BR", "SN"]]], "alternativeSolutions": [[[], [], []], [[], [], []], [["PY", "RS", "SM", "TM"], ["TL"], ["PT"]]], "rows": [{"category": "elevation_sub1k", "value": true}, {"category": "top_20_area", "value": true}, {"category": "flag_colors", "value": "Yellow/Gold"}], "cols": [{"category": "landlocked", "value": true}, {"category": "continent", "value": "OC"}, {"category": "ending_letter", "value": "L"}], "data": {"maxCellDifficulty": 7.681381816184457, "avgCellDifficulty": 4.883911315046509, "difficultyLevel": "hard"}}, {"size": 3, "solutions": [[["AU"], ["AD", "AL", "AT"], ["AF", "AR"]], [["AU"], ["RU"], ["AR", "CA", "CD", "CN", "IN", "IR", "KZ", "MX", "PE", "RU", "US"]], [["PG", "VU"], ["AL", "BE", "DE", "EE"], ["AF", "KE", "TZ", "UG"]]], "alternativeSolutions": [[[], ["AM", "AZ"], []], [[], [], []], [["TL"], [], ["EC"]]], "rows": [{"category": "starting_letter", "value": "A"}, {"category": "top_20_area", "value": true}, {"category": "flag_colors", "value": "Black"}], "cols": [{"category": "continent", "value": "OC"}, {"category": "continent", "value": "EU"}, {"category": "elevation_sup5k", "value": true}], "data": {"maxCellDifficulty": 5.837210048535806, "avgCellDifficulty": 3.6548249520434783, "difficultyLevel": "medium"}}, {"size": 3, "solutions": [[["AR", "BR", "CN"], ["BE", "CH", "DE", "HU", "RO", "RS", "SK"], ["BB", "BN", "KN"]], [["AU", "BR", "CA", "CN", "IN", "KZ", "US"], ["CH", "LI", "MT", "SM"], ["FM", "LK", "MT", "NZ", "PH", "PW", "TT", "TW"]], [["BR", "CD", "CN", "ID", "IN", "IR", "MX", "RU", "US"], ["DE", "RU"], ["ID", "JP", "PH"]]], "alternativeSolutions": [[[], ["AZ"], []], [[], ["TR"], ["AU"]], [[], ["TR"], []]], "rows": [{"category": "capital_starting_letter", "value": "B"}, {"category": "capital_not_largest", "value": true}, {"category": "top_20_population", "value": true}], "cols": [{"category": "top_20_area", "value": true}, {"category": "continent", "value": "EU"}, {"category": "island", "value": true}], "data": {"maxCellDifficulty": 5.210850485900886, "avgCellDifficulty": 2.7718806869474015, "difficultyLevel": "easy"}}, {"size": 3, "solutions": [[["AD", "AG", "BH", "GD", "KN", "LI", "MC", "MT", "MV", "SC", "SG", "TV"], ["LI", "MT", "PW", "SM"], ["AD", "LI", "SM", "VA"]], [["BO", "CL", "CO", "EC", "GY", "PE", "PY", "SR", "VE"], ["BO", "BR", "EC"], ["BO", "PY"]], [["AE", "AF", "AM", "AZ", "BD", "BH", "BN", "CN", "GE", "ID", "IQ", "IR", "JO", "JP", "KG", "KH", "KP", "KR", "KW", "LA", "LB", "LK", "MM", "MN", "MV", "MY", "NP", "OM", "PH", "PS", "QA", "SG", "SY", "TH", "TJ", "TL", "TM", "TR", "TW", "VN", "YE"], ["AE", "CN", "IL", "IN", "KZ", "LK", "MM", "PH", "PK", "TR", "TW", "VN"], ["AF", "AM", "AZ", "BT", "KG", "KZ", "LA", "MN", "NP", "TJ", "TM", "UZ"]]], "alternativeSolutions": [[[], [], []], [["PA", "TT"], ["TT"], []], [["EG", "RU", "UZ"], [], []]], "rows": [{"category": "bottom_20_area", "value": true}, {"category": "continent", "value": "SA"}, {"category": "continent", "value": "AS"}], "cols": [{"category": "flag_colors", "value": "Red"}, {"category": "capital_not_largest", "value": true}, {"category": "landlocked", "value": true}], "data": {"maxCellDifficulty": 6.458534367123542, "avgCellDifficulty": 3.7312858253461254, "difficultyLevel": "medium"}}, {"size": 3, "solutions": [[["CA", "MX", "US"], ["RU"], ["PK"]], [["AG", "BB", "BS", "CU", "DM", "DO", "GD", "HT", "JM", "KN", "LC", "TT", "VC"], ["CY", "GB", "IE", "IS", "MT"], ["PW"]], [["BZ", "CA", "TT", "US"], ["CH", "LI", "MT", "SM"], ["PK", "PW"]]], "alternativeSolutions": [[[], ["GE", "TR"], []], [[], [], []], [[], ["TR"], []]], "rows": [{"category": "elevation_sup5k", "value": true}, {"category": "island", "value": true}, {"category": "capital_not_largest", "value": true}], "cols": [{"category": "continent", "value": "NA"}, {"category": "continent", "value": "EU"}, {"category": "capital_ending_letter", "value": "D"}], "data": {"maxCellDifficulty": 7.5791526142664685, "avgCellDifficulty": 4.194883922924302, "difficultyLevel": "medium"}}, {"size": 3, "solutions": [[["BB", "DK", "EE", "NR", "PY", "TT"], ["IR", "US"], ["BZ", "CH", "NZ", "TT", "US"]], [["FM", "KI", "MH", "NR", "PW", "TV"], ["AU"], ["AU", "FM", "NZ", "PW"]], [["BH", "KW", "MV", "QA", "SG"], ["CN", "ID", "IN", "IR", "KZ", "MN", "SA"], ["AE", "CN", "IL", "IN", "KZ", "LK", "MM", "PH", "PK", "TR", "TW", "VN"]]], "alternativeSolutions": [[[], ["KZ"], ["CI", "KZ", "ZA"]], [[], [], []], [[], ["RU"], []]], "rows": [{"category": "capital_ending_letter", "value": "N"}, {"category": "continent", "value": "OC"}, {"category": "continent", "value": "AS"}], "cols": [{"category": "elevation_sub1k", "value": true}, {"category": "top_20_area", "value": true}, {"category": "capital_not_largest", "value": true}], "data": {"maxCellDifficulty": 7.681381816184457, "avgCellDifficulty": 4.122322641909842, "difficultyLevel": "medium"}}, {"size": 3, "solutions": [[["VN"], ["VU"], ["VA"]], [["MX", "US"], ["AG", "BB", "BS", "DM", "JM", "KN", "LC", "TT"], ["AG", "BB", "BS", "GD", "LC", "TT"]], [["ET"], ["AF", "BW", "LS", "MW", "SS", "SZ", "UG", "ZM", "ZW"], ["BF", "BY", "LU", "MD", "PY", "SM", "VA"]]], "alternativeSolutions": [[[], [], []], [[], [], []], [[], [], []]], "rows": [{"category": "starting_letter", "value": "V"}, {"category": "continent", "value": "NA"}, {"category": "landlocked", "value": true}], "cols": [{"category": "top_20_population", "value": true}, {"category": "flag_colors", "value": "Black"}, {"category": "elevation_sub1k", "value": true}], "data": {"maxCellDifficulty": 6.227286711897431, "avgCellDifficulty": 4.7414343313384215, "difficultyLevel": "hard"}}, {"size": 3, "solutions": [[["BF", "BI", "BW", "CF", "ET", "LS", "ML", "MW", "NE", "RW", "SS", "SZ", "TD", "UG", "ZM", "ZW"], ["AM", "BT", "NE", "ZM"], ["AT", "LA", "LI", "VA"]], [["BI", "BJ", "CI", "CM", "GM", "GQ", "MA", "NG", "TZ", "ZA"], ["CI", "IN", "LK"], ["LI", "MT"]], [["SC"], ["MH"], ["LI", "MT", "SC", "VA"]]], "alternativeSolutions": [[[], [], []], [[], [], []], [[], [], []]], "rows": [{"category": "landlocked", "value": true}, {"category": "capital_not_largest", "value": true}, {"category": "bottom_20_area", "value": true}], "cols": [{"category": "continent", "value": "AF"}, {"category": "flag_colors", "value": "Orange"}, {"category": "capital_starting_letter", "value": "V"}], "data": {"maxCellDifficulty": 8.22458228249608, "avgCellDifficulty": 5.465050961364295, "difficultyLevel": "hard"}}, {"size": 3, "solutions": [[["GY"], ["AR", "BR", "PE"], ["BR"]], [["AF", "KE", "TZ", "UG"], ["AR", "CA", "CD", "CN", "IN", "IR", "KZ", "MX", "PE", "RU", "US"], ["CD", "CN", "IN", "IR", "MX", "PK", "RU", "TR", "US"]], [["AG", "BB", "BN", "BS", "DM", "JM", "KN", "LC", "PG", "ST", "TL", "TT", "VU"], ["ID"], ["ID", "JP", "PH"]]], "alternativeSolutions": [[["EC", "TT"], [], []], [["EC"], [], []], [[], ["AU"], []]], "rows": [{"category": "continent", "value": "SA"}, {"category": "elevation_sup5k", "value": true}, {"category": "island", "value": true}], "cols": [{"category": "flag_colors", "value": "Black"}, {"category": "top_20_area", "value": true}, {"category": "top_20_population", "value": true}], "data": {"maxCellDifficulty": 5.145806732247559, "avgCellDifficulty": 3.259784857633771, "difficultyLevel": "medium"}}, {"size": 3, "solutions": [[["BI", "BJ", "CI", "CM", "GM", "GQ", "MA", "NG", "TZ", "ZA"], ["LI", "MT", "PW", "SM"], ["AU", "BR", "CA", "CN", "IN", "KZ", "US"]], [["CV", "KM", "MG", "MU", "SC", "ST"], ["AG", "BB", "BH", "GD", "KN", "LC", "MH", "MT", "MV", "NR", "PW", "SC", "SG", "TV", "VC"], ["ID"]], [["CI", "NE", "ZM"], ["MH"], ["IN"]]], "alternativeSolutions": [[[], [], []], [[], [], ["AU"]], [[], [], []]], "rows": [{"category": "capital_not_largest", "value": true}, {"category": "island", "value": true}, {"category": "flag_colors", "value": "Orange"}], "cols": [{"category": "continent", "value": "AF"}, {"category": "bottom_20_area", "value": true}, {"category": "top_20_area", "value": true}], "data": {"maxCellDifficulty": 8.22458228249608, "avgCellDifficulty": 4.636516974916482, "difficultyLevel": "hard"}}, {"size": 3, "solutions": [[["CD"], ["ET", "NG", "TR"], ["BR", "CD", "CN", "ID", "IN", "IR", "MX", "RU", "US"]], [["DJ", "DM"], ["AE", "DZ", "ER", "ET", "GH", "JO", "MG", "NG", "TM"], ["BR", "DZ", "IN", "IR", "LY", "MX", "SA", "SD"]], [["DK"], ["AD", "GR", "NL"], ["RU"]]], "alternativeSolutions": [[[], [], []], [[], ["CI", "PY"], []], [[], ["TR"], []]], "rows": [{"category": "top_20_population", "value": true}, {"category": "flag_colors", "value": "Green"}, {"category": "continent", "value": "EU"}], "cols": [{"category": "starting_letter", "value": "D"}, {"category": "capital_starting_letter", "value": "A"}, {"category": "top_20_area", "value": true}], "data": {"maxCellDifficulty": 5.755772374342836, "avgCellDifficulty": 3.2951765141183147, "difficultyLevel": "medium"}}, {"size": 3, "solutions": [[["BI", "BJ", "CI", "CM", "GM", "GQ", "MA", "NG", "TZ", "ZA"], ["AU", "FM", "NZ", "PW"], ["BI", "BO", "CH", "KZ", "LI", "SM"]], [["SC"], ["MH", "NR", "PW", "TV"], ["AD", "LI", "SM", "VA"]], [["TG", "TN", "TZ"], ["TO", "TV"], ["TJ", "TM"]]], "alternativeSolutions": [[[], [], []], [[], [], []], [[], ["TL"], []]], "rows": [{"category": "capital_not_largest", "value": true}, {"category": "bottom_20_area", "value": true}, {"category": "starting_letter", "value": "T"}], "cols": [{"category": "continent", "value": "AF"}, {"category": "continent", "value": "OC"}, {"category": "landlocked", "value": true}], "data": {"maxCellDifficulty": 8.08798374048573, "avgCellDifficulty": 5.565733703110636, "difficultyLevel": "hard"}}, {"size": 3, "solutions": [[["CD", "MX"], ["AR", "BR", "CN"], ["ID"]], [["BF", "CD", "CG", "ME", "TG", "XK"], ["BB", "BE", "BN", "BR", "CF", "CG", "CN", "CO", "DE", "GW", "KG", "KN", "ML", "RO"], ["AG", "BB", "BN", "BS", "CV", "CY", "DM", "FJ", "GD", "JM", "KI", "KM", "KN", "LC", "LK", "MU", "NR", "PG", "PH", "PW", "SB", "SC", "ST", "TL", "TV", "VC", "VU"]], [["CD", "MX"], ["BR", "CN", "DE", "TH"], ["ID", "JP", "PH"]]], "alternativeSolutions": [[[], [], ["AU"]], [["SM"], ["AR", "RS", "ZA"], []], [[], [], []]], "rows": [{"category": "top_20_area", "value": true}, {"category": "flag_colors", "value": "Yellow/Gold"}, {"category": "top_20_population", "value": true}], "cols": [{"category": "ending_letter", "value": "O"}, {"category": "capital_starting_letter", "value": "B"}, {"category": "island", "value": true}], "data": {"maxCellDifficulty": 5.519085989797467, "avgCellDifficulty": 3.3395261590670966, "difficultyLevel": "easy"}}, {"size": 3, "solutions": [[["DE", "EG"], ["EG"], ["BD", "CN", "ID", "IN", "IR", "JP", "PH", "PK", "TH", "TR", "VN"]], [["AE", "TT", "TZ", "ZA"], ["AU", "LK"], ["AE", "CN", "IL", "IN", "KZ", "LK", "MM", "PH", "PK", "TR", "TW", "VN"]], [["AG", "BB", "BS", "BW", "EE", "KR", "LC", "LS", "SS", "SZ", "TZ", "ZA"], ["AU", "LC", "MD", "VE"], ["AM", "AZ", "IL", "IN", "KH", "KP", "KR", "KZ", "LA", "MN", "MY", "NP", "PH", "TH", "TW", "UZ"]]], "alternativeSolutions": [[[], [], ["EG", "RU"]], [["EC"], ["ZA"], []], [["EC"], ["ZA"], ["RU"]]], "rows": [{"category": "top_20_population", "value": true}, {"category": "capital_not_largest", "value": true}, {"category": "flag_colors", "value": "Blue"}], "cols": [{"category": "flag_colors", "value": "Black"}, {"category": "capital_starting_letter", "value": "C"}, {"category": "continent", "value": "AS"}], "data": {"maxCellDifficulty": 3.947526669622755, "avgCellDifficulty": 2.7390507027586066, "difficultyLevel": "easy"}}, {"size": 3, "solutions": [[["CD", "EG", "ET", "NG"], ["ID", "JP", "PH"], ["MX", "US"]], [["AO", "BI", "CD", "CV", "ER", "ET", "GH", "LR", "NG", "SC", "SS", "TD", "TZ", "UG", "ZA", "ZM"], ["BH", "CU", "CV", "CY", "FJ", "ID", "KI", "MT", "PH", "SB", "SC", "TO", "VU", "WS"], ["CA", "CU", "HN", "NI"]], [["BF", "CD", "CG", "LS", "MA", "TG"], ["TT"], ["MX", "TT"]]], "alternativeSolutions": [[[], [], []], [["SZ"], ["AU"], []], [[], [], []]], "rows": [{"category": "top_20_population", "value": true}, {"category": "capital_ending_letter", "value": "A"}, {"category": "ending_letter", "value": "O"}], "cols": [{"category": "continent", "value": "AF"}, {"category": "island", "value": true}, {"category": "continent", "value": "NA"}], "data": {"maxCellDifficulty": 6.022722868799172, "avgCellDifficulty": 3.9567902772537624, "difficultyLevel": "medium"}}, {"size": 3, "solutions": [[["BI", "ML", "MW", "SZ"], ["BI", "DJ", "ML", "MW"], ["BI"]], [["AF", "BO", "BT", "KG", "KZ", "NP", "TJ", "UG"], ["AF", "BO", "IN", "IR", "KE", "MM", "MX", "PK", "TJ", "TZ"], ["BO", "CA", "CN", "EC", "IN", "KZ", "MM", "PK", "TR", "TZ", "US"]], [["BF", "BY", "LU", "MD", "PY", "SM", "VA"], ["BF", "BJ", "BY", "GD", "GH", "GM", "GW", "KW", "LT", "MR", "MU", "MV", "SC", "SN", "TG"], ["BJ", "FM", "GM", "MT", "PW", "SM", "TT"]]], "alternativeSolutions": [[[], ["HT"], []], [[], [], []], [[], ["PY", "SM"], []]], "rows": [{"category": "ending_letter", "value": "I"}, {"category": "elevation_sup5k", "value": true}, {"category": "elevation_sub1k", "value": true}], "cols": [{"category": "landlocked", "value": true}, {"category": "flag_colors", "value": "Green"}, {"category": "capital_not_largest", "value": true}], "data": {"maxCellDifficulty": 6.61574693194475, "avgCellDifficulty": 4.9589991203812005, "difficultyLevel": "hard"}}, {"size": 3, "solutions": [[["TL", "TO", "TT", "TV", "TW"], ["HT", "KN", "MV", "SG", "ST"], ["FM", "LK", "MT", "NZ", "PH", "PW", "TT", "TW"]], [["TJ", "TM"], ["BW", "CZ", "LA", "MK", "MW", "RS", "SZ", "TJ", "ZW"], ["BI", "BO", "CH", "KZ", "LI", "SM"]], [["TO", "TV"], ["KN"], ["FM", "LI", "PW", "SM"]]], "alternativeSolutions": [[[], ["LK"], ["AU"]], [[], ["BO"], []], [[], [], []]], "rows": [{"category": "island", "value": true}, {"category": "landlocked", "value": true}, {"category": "bottom_20_population", "value": true}], "cols": [{"category": "starting_letter", "value": "T"}, {"category": "capital_ending_letter", "value": "E"}, {"category": "capital_not_largest", "value": true}], "data": {"maxCellDifficulty": 8.612023235358304, "avgCellDifficulty": 5.776071974854189, "difficultyLevel": "hard"}}, {"size": 3, "solutions": [[["GM"], ["AF", "KR"], ["AF"]], [["CD", "DZ", "LY", "SD", "TD"], ["LY", "SD"], ["KZ", "MN", "TD"]], [["EG", "ER", "ET", "GQ", "SZ"], ["EE", "EG", "SZ"], ["ET", "SZ"]]], "alternativeSolutions": [[[], [], []], [[], [], []], [[], ["EC"], []]], "rows": [{"category": "capital_ending_letter", "value": "L"}, {"category": "top_20_area", "value": true}, {"category": "starting_letter", "value": "E"}], "cols": [{"category": "continent", "value": "AF"}, {"category": "flag_colors", "value": "Black"}, {"category": "landlocked", "value": true}], "data": {"maxCellDifficulty": 7.280922206876049, "avgCellDifficulty": 4.907964940923005, "difficultyLevel": "hard"}}, {"size": 3, "solutions": [[["FM", "LI", "PW", "SM"], ["BR", "CN", "IN", "NG", "PH", "PK", "TR", "US", "VN"], ["CA"]], [["AG", "DM", "FM", "KI", "KN", "LC", "MC", "MH", "NR", "SC", "SM", "TO", "TV", "VA", "WS"], ["BR", "EG", "ID", "IN", "IR", "JP", "MX", "NG", "PH", "PK", "RU", "TH", "TR", "US"], ["CA", "NO"]], [["AD", "AG", "DM", "FM", "GD", "LC", "TO", "WS"], ["CN", "ET", "ID", "IN", "NG", "RU"], ["CA"]]], "alternativeSolutions": [[[], [], []], [[], [], []], [[], ["US"], []]], "rows": [{"category": "capital_not_largest", "value": true}, {"category": "flag_colors", "value": "White"}, {"category": "ending_letter", "value": "A"}], "cols": [{"category": "bottom_20_population", "value": true}, {"category": "top_20_population", "value": true}, {"category": "capital_starting_letter", "value": "O"}], "data": {"maxCellDifficulty": 6.654639793752897, "avgCellDifficulty": 3.543276294421264, "difficultyLevel": "medium"}}, {"size": 3, "solutions": [[["AU", "FJ", "FM", "KI", "MH", "NR", "NZ", "PG", "SB", "TO", "TV", "WS"], ["AR", "AU", "BR", "CA", "DZ", "ID", "IN", "IR", "LY", "MX", "PE", "RU", "SA", "SD", "US"], ["KP", "NA", "NE", "NG", "NI", "NL", "NO", "NP", "NR", "NZ"]], [["PW", "TO"], ["IN", "TD"], ["NE"]], [["SB", "VU"], ["BR", "DZ", "IN", "IR", "LY", "MX", "SA", "SD"], ["NA", "NE", "NG"]]], "alternativeSolutions": [[["TL"], [], []], [[], ["KZ"], []], [[], [], []]], "rows": [{"category": "flag_colors", "value": "White"}, {"category": "capital_starting_letter", "value": "N"}, {"category": "flag_colors", "value": "Green"}], "cols": [{"category": "continent", "value": "OC"}, {"category": "top_20_area", "value": true}, {"category": "starting_letter", "value": "N"}], "data": {"maxCellDifficulty": 7.476386573049067, "avgCellDifficulty": 4.1374656147493125, "difficultyLevel": "medium"}}, {"size": 3, "solutions": [[["RU"], ["CA"], ["CD", "CN", "IN", "IR", "MX", "PK", "RU", "TR", "US"]], [["CH", "LI", "MT", "SM"], ["CA"], ["BR", "CN", "IN", "NG", "PH", "PK", "TR", "US", "VN"]], [["AD", "AT", "BY", "CH", "CZ", "HU", "LI", "LU", "MD", "MK", "RS", "SK", "SM", "VA", "XK"], ["BF"], ["ET"]]], "alternativeSolutions": [[["GE", "TR"], [], []], [["TR"], [], []], [["AM", "AZ"], [], []]], "rows": [{"category": "elevation_sup5k", "value": true}, {"category": "capital_not_largest", "value": true}, {"category": "landlocked", "value": true}], "cols": [{"category": "continent", "value": "EU"}, {"category": "capital_starting_letter", "value": "O"}, {"category": "top_20_population", "value": true}], "data": {"maxCellDifficulty": 5.534603540603029, "avgCellDifficulty": 3.2902862528832015, "difficultyLevel": "medium"}}, {"size": 3, "solutions": [[["AU", "BR", "CA", "CN", "IN", "KZ", "US"], ["BJ", "CM", "KZ", "LI", "PK", "TW"], ["FM", "LK", "MT", "NZ", "PH", "PW", "TT", "TW"]], [["ID"], ["SS"], ["ID"]], [["IN"], ["BT"], ["IE", "LK", "MH"]]], "alternativeSolutions": [[[], [], ["AU"]], [[], [], []], [[], [], []]], "rows": [{"category": "capital_not_largest", "value": true}, {"category": "capital_starting_letter", "value": "J"}, {"category": "flag_colors", "value": "Orange"}], "cols": [{"category": "top_20_area", "value": true}, {"category": "ending_letter", "value": "N"}, {"category": "island", "value": true}], "data": {"maxCellDifficulty": 6.486618509600383, "avgCellDifficulty": 4.128530096657274, "difficultyLevel": "medium"}}, {"size": 3, "solutions": [[["CU", "FI", "VN", "ZW"], ["FI"], ["ZW"]], [["AG", "BE", "BF", "BH", "BJ", "BY", "DK", "GD", "GH", "GM", "GW", "KI", "KW", "LT", "LU", "LV", "MC", "MD", "MR", "MT", "MU", "MV", "NL", "PY", "QA", "SC", "SG", "SN", "TG", "TT", "TV"], ["BE", "BY", "DK", "EE", "LT", "LU", "LV", "MC", "MD", "MT", "NL", "SM", "VA"], ["AG", "BB", "BE", "BS", "EE", "GH", "GW", "KW", "LC", "TT"]], [["AF", "BO", "CA", "CD", "CL", "CN", "CO", "EC", "GE", "IR", "KE", "KG", "MM", "MX", "NP", "PE", "RU", "TJ", "TR", "UG", "US"], ["RU"], ["AF", "KE", "TZ", "UG"]]], "alternativeSolutions": [[[], [], []], [[], [], []], [[], ["GE", "TR"], ["EC"]]], "rows": [{"category": "capital_starting_letter", "value": "H"}, {"category": "elevation_sub1k", "value": true}, {"category": "elevation_sup5k", "value": true}], "cols": [{"category": "flag_colors", "value": "Red"}, {"category": "continent", "value": "EU"}, {"category": "flag_colors", "value": "Black"}], "data": {"maxCellDifficulty": 5.210006540094993, "avgCellDifficulty": 3.58884368357204, "difficultyLevel": "medium"}}, {"size": 3, "solutions": [[["GD", "GT"], ["DE", "GH", "GW", "GY"], ["GE"]], [["CA", "MX", "US"], ["AF", "KE", "TZ", "UG"], ["AF", "BT", "CN", "GE", "IN", "IR", "KG", "KZ", "MM", "NP", "PK", "TJ", "TR"]], [["AG", "BB", "GD", "KN", "LC", "VC"], ["AG", "BB", "KN", "LC"], ["BH", "MV", "SG"]]], "alternativeSolutions": [[[], [], []], [[], ["EC"], ["RU"]], [[], [], []]], "rows": [{"category": "starting_letter", "value": "G"}, {"category": "elevation_sup5k", "value": true}, {"category": "bottom_20_area", "value": true}], "cols": [{"category": "continent", "value": "NA"}, {"category": "flag_colors", "value": "Black"}, {"category": "continent", "value": "AS"}], "data": {"maxCellDifficulty": 6.461257735798235, "avgCellDifficulty": 4.443071306530415, "difficultyLevel": "hard"}}, {"size": 3, "solutions": [[["ET"], ["BI", "BO", "CH", "KZ", "LI", "SM"], ["KZ", "MN", "TD"]], [["ID"], ["IL"], ["ID"]], [["CD", "EG", "ET", "NG"], ["BI", "BJ", "CI", "CM", "GM", "GQ", "MA", "NG", "TZ", "ZA"], ["CD", "DZ", "LY", "SD", "TD"]]], "alternativeSolutions": [[[], [], []], [[], [], []], [[], [], []]], "rows": [{"category": "landlocked", "value": true}, {"category": "capital_starting_letter", "value": "J"}, {"category": "continent", "value": "AF"}], "cols": [{"category": "top_20_population", "value": true}, {"category": "capital_not_largest", "value": true}, {"category": "top_20_area", "value": true}], "data": {"maxCellDifficulty": 4.336098569401109, "avgCellDifficulty": 3.5922875566245205, "difficultyLevel": "medium"}}, {"size": 3, "solutions": [[["BF", "BY", "LU", "MD", "PY", "SM", "VA"], ["BF", "BJ", "GH", "GM", "GW", "MR", "MU", "SC", "SN", "TG"], ["AG", "BB", "BS", "EE", "FM", "GM", "KI", "LC", "LU", "MD", "MH", "MU", "NL", "NR", "PW", "PY", "SC", "SM", "TV", "UY"]], [["AF", "BW", "LS", "MW", "SS", "SZ", "UG", "ZM", "ZW"], ["AO", "BW", "EG", "GH", "GW", "KE", "LS", "LY", "MW", "MZ", "SD", "SS", "ST", "SZ", "TZ", "UG", "ZA", "ZM", "ZW"], ["AG", "BB", "BS", "BW", "EE", "KR", "LC", "LS", "SS", "SZ", "TZ", "ZA"]], [["ET"], ["CD", "EG", "ET", "NG"], ["BR", "CD", "ET", "IN", "PH", "RU", "TH", "US"]]], "alternativeSolutions": [[[], [], []], [[], [], ["EC"]], [[], [], []]], "rows": [{"category": "elevation_sub1k", "value": true}, {"category": "flag_colors", "value": "Black"}, {"category": "top_20_population", "value": true}], "cols": [{"category": "landlocked", "value": true}, {"category": "continent", "value": "AF"}, {"category": "flag_colors", "value": "Blue"}], "data": {"maxCellDifficulty": 5.487563275556228, "avgCellDifficulty": 3.73407063475045, "difficultyLevel": "easy"}}, {"size": 3, "solutions": [[["GY", "PY"], ["BO", "BR", "EC"], ["AR", "BO", "CL", "CO", "EC", "PE"]], [["AM", "IE"], ["CI", "IN", "LK"], ["BT", "IN"]], [["PT"], ["BR", "IL"], ["NP"]]], "alternativeSolutions": [[["TT"], ["TT"], []], [["CI"], [], []], [[], [], []]], "rows": [{"category": "continent", "value": "SA"}, {"category": "flag_colors", "value": "Orange"}, {"category": "ending_letter", "value": "L"}], "cols": [{"category": "capital_ending_letter", "value": "N"}, {"category": "capital_not_largest", "value": true}, {"category": "elevation_sup5k", "value": true}], "data": {"maxCellDifficulty": 5.681987261091219, "avgCellDifficulty": 4.53855867402691, "difficultyLevel": "hard"}}, {"size": 3, "solutions": [[["AU", "CA", "CD", "CN", "DZ", "ID", "IR", "LY", "MN", "MX", "PE", "RU", "SD", "TD", "US"], ["LY", "SD"], ["IR", "LY"]], [["AG", "BE", "BF", "BH", "BJ", "BY", "DK", "GD", "GH", "GM", "GW", "KI", "KW", "LT", "LU", "LV", "MC", "MD", "MR", "MT", "MU", "MV", "NL", "PY", "QA", "SC", "SG", "SN", "TG", "TT", "TV"], ["AG", "BB", "BE", "BS", "EE", "GH", "GW", "KW", "LC", "TT"], ["EE", "KI"]], [["JO", "JP"], ["JM", "JO"], ["JP"]]], "alternativeSolutions": [[[], [], []], [[], [], ["NL"]], [[], [], []]], "rows": [{"category": "top_20_area", "value": true}, {"category": "elevation_sub1k", "value": true}, {"category": "starting_letter", "value": "J"}], "cols": [{"category": "flag_colors", "value": "Red"}, {"category": "flag_colors", "value": "Black"}, {"category": "capital_starting_letter", "value": "T"}], "data": {"maxCellDifficulty": 6.122411916265606, "avgCellDifficulty": 3.677958372023857, "difficultyLevel": "medium"}}]